Workbook

Sheet Assumptions
A1: Resonate — Unit Economics Model (2026-07). Edit BLUE cells.
A3: Assumption | B3: Conservative | C3: Base | D3: Ambitious | E3: Unit / Source
A4: 1. Shows campaign fee (Phase 1)
A5: Funded campaigns / month | B5: 1 | C5: 2 | D5: 5 | E5: Wedge: international niche scenes (docs/rfc/business-model.md)
A6: Avg funded campaign size (USD) | B6: 3000 | C6: 6000 | D6: 12000 | E6: Assumption; small venue budget range
A7: Platform fee (success-only) | B7: 0.06 | C7: 0.06 | D7: 0.06 | E7: ADR-BM-1 proposed 6%; comp: Kickstarter 5% + processing
A9: 2. Artist Pro — creator SaaS (Phase 2)
A10: Paying artists (subscribers) | B10: 25 | C10: 75 | D10: 250 | E10: Phase-2 target: 50 paying artists (review §4)
A11: Price / month (USD) | B11: 19.99 | C11: 19.99 | D11: 19.99 | E11: Comp: BeatStars $19.99/mo, Splice $9.99+/mo, DistroKid $24.99/yr
A12: % of artists buying extra generation credits | B12: 0.3 | C12: 0.3 | D12: 0.3 | E12: Assumption
A13: Avg overage credit spend / buying artist / mo (USD) | B13: 5 | C13: 10 | D13: 20 | E13: ADR-BM-3; credit price ~$0.10/30s vs cost $0.06/30s (generation.service.ts)
A14: Platform gross margin on credits | B14: 0.35 | C14: 0.35 | D14: 0.35 | E14: ADR-BM-3 proposed 30–50% margin over GPU cost
A16: 3. Marketplace take-rate (Phase 2)
A17: Marketplace GMV / month (USD) | B17: 1000 | C17: 7500 | D17: 30000 | E17: Stems, downloads, remix licenses, punchline drops
A18: Platform take-rate | B18: 0.1 | C18: 0.1 | D18: 0.1 | E18: ADR-BM-2 proposed 10% (15% micro); comp: Bandcamp 10–15%; current contract default 0.5%
A20: 4. Listener Pro (Phase 3)
A21: Subscribers | B21: 0 | C21: 250 | D21: 1500 | E21: Launch gate: 500–1,000 genuine WAU in wedge communities
A22: Price / month (USD) | B22: 9.99 | C22: 9.99 | D22: 9.99 | E22: docs/rfc/business-model.md Layer 2
A23: Wallet pre-fund portion (USD) | B23: 5 | C23: 5 | D23: 5 | E23: RFC: ~$5 of subscription pre-funds agent wallet (USDC)
A24: Share of pre-fund actually spent / month | B24: 0.8 | C24: 0.8 | D24: 0.8 | E24: Assumption; unspent rolls over
A25: Platform take on micro-spend | B25: 0.15 | C25: 0.15 | D25: 0.15 | E25: RFC 85/15 micro-payment split
A27: 5. B2B & agent licensing (Phase 4)
A28: Licenses closed / month | B28: 0 | C28: 0.5 | D28: 2 | E28: Sync/commercial/agent deals; long sales cycle
A29: Avg license value (USD) | B29: 1000 | C29: 2500 | D29: 5000 | E29: RFC commercial $50–5,000+, sync $500–50,000 (negotiated)
A30: Platform take | B30: 0.1 | C30: 0.1 | D30: 0.1 | E30: ADR-BM-2 / RFC 10%
A32: Reference costs
A33: AI generation cost per 30s (USD) | B33: 0.06 | C33: 0.06 | D33: 0.06 | E33: Source: backend/src/modules/generation/generation.service.ts COST_PER_30_SECONDS
A34: Proposed credit price per 30s (USD) | B34: 0.1 | C34: 0.1 | D34: 0.1 | E34: ADR-BM-3
A36: Ramp parameters (Base scenario → Ramp sheet; month 1 = Jul 2026)
A37: Revenue line | B37: Start month # | C37: Ramp months
A38: Shows campaign fee | B38: 3 | C38: 4
A39: Artist Pro (incl. credits) | B39: 5 | C39: 4
A40: Marketplace take | B40: 5 | C40: 6
A41: Listener Pro | B41: 9 | C41: 6
A42: B2B & agent licensing | B42: 13 | C42: 6

Sheet Scenarios
A1: Monthly platform revenue by scenario (steady state, all lines active)
A3: Revenue line | B3: Conservative | C3: Base | D3: Ambitious | E3: Formula
A4: Shows campaign fee | B4: =Assumptions!B5*Assumptions!B6*Assumptions!B7 | C4: =Assumptions!C5*Assumptions!C6*Assumptions!C7 | D4: =Assumptions!D5*Assumptions!D6*Assumptions!D7 | E4: campaigns × size × 6% fee
A5: Artist Pro subscriptions | B5: =Assumptions!B10*Assumptions!B11 | C5: =Assumptions!C10*Assumptions!C11 | D5: =Assumptions!D10*Assumptions!D11 | E5: artists × $19.99
A6: Generation credits (gross profit) | B6: =Assumptions!B10*Assumptions!B12*Assumptions!B13*Assumptions!B14 | C6: =Assumptions!C10*Assumptions!C12*Assumptions!C13*Assumptions!C14 | D6: =Assumptions!D10*Assumptions!D12*Assumptions!D13*Assumptions!D14 | E6: artists × buyer% × spend × margin
A7: Marketplace take | B7: =Assumptions!B17*Assumptions!B18 | C7: =Assumptions!C17*Assumptions!C18 | D7: =Assumptions!D17*Assumptions!D18 | E7: GMV × 10%
A8: Listener Pro (subs + micro-take) | B8: =Assumptions!B21*(Assumptions!B22-Assumptions!B23)+Assumptions!B21*Assumptions!B23*Assumptions!B24*Assumptions!B25 | C8: =Assumptions!C21*(Assumptions!C22-Assumptions!C23)+Assumptions!C21*Assumptions!C23*Assumptions!C24*Assumptions!C25 | D8: =Assumptions!D21*(Assumptions!D22-Assumptions!D23)+Assumptions!D21*Assumptions!D23*Assumptions!D24*Assumptions!D25 | E8: subs × ($9.99 − $5 pre-fund) + micro-spend × 15%
A9: B2B & agent licensing | B9: =Assumptions!B28*Assumptions!B29*Assumptions!B30 | C9: =Assumptions!C28*Assumptions!C29*Assumptions!C30 | D9: =Assumptions!D28*Assumptions!D29*Assumptions!D30 | E9: deals × value × 10%
A10: Total platform MRR | B10: =SUM(B4:B9) | C10: =SUM(C4:C9) | D10: =SUM(D4:D9)
A11: Implied ARR | B11: =B10*12 | C11: =C10*12 | D11: =D10*12
A13: Monthly $ routed to artists (est.) | B13: =Assumptions!B5*Assumptions!B6*(1-Assumptions!B7)+Assumptions!B17*(1-Assumptions!B18)+Assumptions!B21*Assumptions!B23*Assumptions!B24*(1-Assumptions!B25)+Assumptions!B28*Assumptions!B29*(1-Assumptions!B30) | C13: =Assumptions!C5*Assumptions!C6*(1-Assumptions!C7)+Assumptions!C17*(1-Assumptions!C18)+Assumptions!C21*Assumptions!C23*Assumptions!C24*(1-Assumptions!C25)+Assumptions!C28*Assumptions!C29*(1-Assumptions!C30) | D13: =Assumptions!D5*Assumptions!D6*(1-Assumptions!D7)+Assumptions!D17*(1-Assumptions!D18)+Assumptions!D21*Assumptions!D23*Assumptions!D24*(1-Assumptions!D25)+Assumptions!D28*Assumptions!D29*(1-Assumptions!D30) | E13: North-star input: median take-home per active artist = this ÷ active artists

Sheet Ramp (Base)
A1: 18-month activation ramp — Base scenario, phases per roadmap (review §4)
B2: Jul-26 | C2: Aug-26 | D2: Sep-26 | E2: Oct-26 | F2: Nov-26 | G2: Dec-26 | H2: Jan-27 | I2: Feb-27 | J2: Mar-27 | K2: Apr-27 | L2: May-27 | M2: Jun-27 | N2: Jul-27 | O2: Aug-27 | P2: Sep-27 | Q2: Oct-27 | R2: Nov-27 | S2: Dec-27
A3: month # | B3: 1 | C3: 2 | D3: 3 | E3: 4 | F3: 5 | G3: 6 | H3: 7 | I3: 8 | J3: 9 | K3: 10 | L3: 11 | M3: 12 | N3: 13 | O3: 14 | P3: 15 | Q3: 16 | R3: 17 | S3: 18
A4: Shows campaign fee | B4: =IF(B$3>=Assumptions!$B$38,Scenarios!$C$4*MIN(1,(B$3-Assumptions!$B$38+1)/Assumptions!$C$38),0) | C4: =IF(C$3>=Assumptions!$B$38,Scenarios!$C$4*MIN(1,(C$3-Assumptions!$B$38+1)/Assumptions!$C$38),0) | D4: =IF(D$3>=Assumptions!$B$38,Scenarios!$C$4*MIN(1,(D$3-Assumptions!$B$38+1)/Assumptions!$C$38),0) | E4: =IF(E$3>=Assumptions!$B$38,Scenarios!$C$4*MIN(1,(E$3-Assumptions!$B$38+1)/Assumptions!$C$38),0) | F4: =IF(F$3>=Assumptions!$B$38,Scenarios!$C$4*MIN(1,(F$3-Assumptions!$B$38+1)/Assumptions!$C$38),0) | G4: =IF(G$3>=Assumptions!$B$38,Scenarios!$C$4*MIN(1,(G$3-Assumptions!$B$38+1)/Assumptions!$C$38),0) | H4: =IF(H$3>=Assumptions!$B$38,Scenarios!$C$4*MIN(1,(H$3-Assumptions!$B$38+1)/Assumptions!$C$38),0) | I4: =IF(I$3>=Assumptions!$B$38,Scenarios!$C$4*MIN(1,(I$3-Assumptions!$B$38+1)/Assumptions!$C$38),0) | ... S4: =IF(S$3>=Assumptions!$B$38,Scenarios!$C$4*MIN(1,(S$3-Assumptions!$B$38+1)/Assumptions!$C$38),0)
A5: Artist Pro (subs + credits) | B5: =IF(B$3>=Assumptions!$B$39,(Scenarios!$C$5+Scenarios!$C$6)*MIN(1,(B$3-Assumptions!$B$39+1)/Assumptions!$C$39),0) | C5: =IF(C$3>=Assumptions!$B$39,(Scenarios!$C$5+Scenarios!$C$6)*MIN(1,(C$3-Assumptions!$B$39+1)/Assumptions!$C$39),0) | D5: =IF(D$3>=Assumptions!$B$39,(Scenarios!$C$5+Scenarios!$C$6)*MIN(1,(D$3-Assumptions!$B$39+1)/Assumptions!$C$39),0) | E5: =IF(E$3>=Assumptions!$B$39,(Scenarios!$C$5+Scenarios!$C$6)*MIN(1,(E$3-Assumptions!$B$39+1)/Assumptions!$C$39),0) | F5: =IF(F$3>=Assumptions!$B$39,(Scenarios!$C$5+Scenarios!$C$6)*MIN(1,(F$3-Assumptions!$B$39+1)/Assumptions!$C$39),0) | G5: =IF(G$3>=Assumptions!$B$39,(Scenarios!$C$5+Scenarios!$C$6)*MIN(1,(G$3-Assumptions!$B$39+1)/Assumptions!$C$39),0) | H5: =IF(H$3>=Assumptions!$B$39,(Scenarios!$C$5+Scenarios!$C$6)*MIN(1,(H$3-Assumptions!$B$39+1)/Assumptions!$C$39),0) | I5: =IF(I$3>=Assumptions!$B$39,(Scenarios!$C$5+Scenarios!$C$6)*MIN(1,(I$3-Assumptions!$B$39+1)/Assumptions!$C$39),0) | ... S5: =IF(S$3>=Assumptions!$B$39,(Scenarios!$C$5+Scenarios!$C$6)*MIN(1,(S$3-Assumptions!$B$39+1)/Assumptions!$C$39),0)
A6: Marketplace take | B6: =IF(B$3>=Assumptions!$B$40,Scenarios!$C$7*MIN(1,(B$3-Assumptions!$B$40+1)/Assumptions!$C$40),0) | C6: =IF(C$3>=Assumptions!$B$40,Scenarios!$C$7*MIN(1,(C$3-Assumptions!$B$40+1)/Assumptions!$C$40),0) | D6: =IF(D$3>=Assumptions!$B$40,Scenarios!$C$7*MIN(1,(D$3-Assumptions!$B$40+1)/Assumptions!$C$40),0) | E6: =IF(E$3>=Assumptions!$B$40,Scenarios!$C$7*MIN(1,(E$3-Assumptions!$B$40+1)/Assumptions!$C$40),0) | F6: =IF(F$3>=Assumptions!$B$40,Scenarios!$C$7*MIN(1,(F$3-Assumptions!$B$40+1)/Assumptions!$C$40),0) | G6: =IF(G$3>=Assumptions!$B$40,Scenarios!$C$7*MIN(1,(G$3-Assumptions!$B$40+1)/Assumptions!$C$40),0) | H6: =IF(H$3>=Assumptions!$B$40,Scenarios!$C$7*MIN(1,(H$3-Assumptions!$B$40+1)/Assumptions!$C$40),0) | I6: =IF(I$3>=Assumptions!$B$40,Scenarios!$C$7*MIN(1,(I$3-Assumptions!$B$40+1)/Assumptions!$C$40),0) | ... S6: =IF(S$3>=Assumptions!$B$40,Scenarios!$C$7*MIN(1,(S$3-Assumptions!$B$40+1)/Assumptions!$C$40),0)
A7: Listener Pro | B7: =IF(B$3>=Assumptions!$B$41,Scenarios!$C$8*MIN(1,(B$3-Assumptions!$B$41+1)/Assumptions!$C$41),0) | C7: =IF(C$3>=Assumptions!$B$41,Scenarios!$C$8*MIN(1,(C$3-Assumptions!$B$41+1)/Assumptions!$C$41),0) | D7: =IF(D$3>=Assumptions!$B$41,Scenarios!$C$8*MIN(1,(D$3-Assumptions!$B$41+1)/Assumptions!$C$41),0) | E7: =IF(E$3>=Assumptions!$B$41,Scenarios!$C$8*MIN(1,(E$3-Assumptions!$B$41+1)/Assumptions!$C$41),0) | F7: =IF(F$3>=Assumptions!$B$41,Scenarios!$C$8*MIN(1,(F$3-Assumptions!$B$41+1)/Assumptions!$C$41),0) | G7: =IF(G$3>=Assumptions!$B$41,Scenarios!$C$8*MIN(1,(G$3-Assumptions!$B$41+1)/Assumptions!$C$41),0) | H7: =IF(H$3>=Assumptions!$B$41,Scenarios!$C$8*MIN(1,(H$3-Assumptions!$B$41+1)/Assumptions!$C$41),0) | I7: =IF(I$3>=Assumptions!$B$41,Scenarios!$C$8*MIN(1,(I$3-Assumptions!$B$41+1)/Assumptions!$C$41),0) | ... S7: =IF(S$3>=Assumptions!$B$41,Scenarios!$C$8*MIN(1,(S$3-Assumptions!$B$41+1)/Assumptions!$C$41),0)
A8: B2B & agent licensing | B8: =IF(B$3>=Assumptions!$B$42,Scenarios!$C$9*MIN(1,(B$3-Assumptions!$B$42+1)/Assumptions!$C$42),0) | C8: =IF(C$3>=Assumptions!$B$42,Scenarios!$C$9*MIN(1,(C$3-Assumptions!$B$42+1)/Assumptions!$C$42),0) | D8: =IF(D$3>=Assumptions!$B$42,Scenarios!$C$9*MIN(1,(D$3-Assumptions!$B$42+1)/Assumptions!$C$42),0) | E8: =IF(E$3>=Assumptions!$B$42,Scenarios!$C$9*MIN(1,(E$3-Assumptions!$B$42+1)/Assumptions!$C$42),0) | F8: =IF(F$3>=Assumptions!$B$42,Scenarios!$C$9*MIN(1,(F$3-Assumptions!$B$42+1)/Assumptions!$C$42),0) | G8: =IF(G$3>=Assumptions!$B$42,Scenarios!$C$9*MIN(1,(G$3-Assumptions!$B$42+1)/Assumptions!$C$42),0) | H8: =IF(H$3>=Assumptions!$B$42,Scenarios!$C$9*MIN(1,(H$3-Assumptions!$B$42+1)/Assumptions!$C$42),0) | I8: =IF(I$3>=Assumptions!$B$42,Scenarios!$C$9*MIN(1,(I$3-Assumptions!$B$42+1)/Assumptions!$C$42),0) | ... S8: =IF(S$3>=Assumptions!$B$42,Scenarios!$C$9*MIN(1,(S$3-Assumptions!$B$42+1)/Assumptions!$C$42),0)
A9: Total platform MRR | B9: =SUM(B4:B8) | C9: =SUM(C4:C8) | D9: =SUM(D4:D8) | E9: =SUM(E4:E8) | F9: =SUM(F4:F8) | G9: =SUM(G4:G8) | H9: =SUM(H4:H8) | I9: =SUM(I4:I8) | ... S9: =SUM(S4:S8)
